gscPack/__init__.py
gscPack/gscPack.py
gscPack-0.1.0.dist-info/METADATA
gscPack-0.1.0.dist-info/RECORD
gscPack-0.1.0.dist-info/WHEEL
gscPack-0.1.0.dist-info/top_level.txt
