Metadata-Version: 2.1
Name: gscPack
Version: 0.1.0
Summary: This package assists in the creation and manipulation of gsc (Gravestroke Seperated Coloumns) files.
Home-page: https://github.com/Trek1492/gscPack
Author: Samuel Mansfield
Author-email: samueljmansfield@gmail.com
License: UNKNOWN
Platform: UNKNOWN
Classifier: Programming Language :: Python :: 3
Classifier: License :: OSI Approved :: MIT License
Classifier: Operating System :: Microsoft :: Windows
